dialog_api/__init__.py
dialog_api/authentication_pb2.py
dialog_api/authentication_pb2_grpc.py
dialog_api/clickroad_pb2.py
dialog_api/clickroad_pb2_grpc.py
dialog_api/config_sync_pb2.py
dialog_api/config_sync_pb2_grpc.py
dialog_api/contacts_pb2.py
dialog_api/contacts_pb2_grpc.py
dialog_api/counters_pb2.py
dialog_api/counters_pb2_grpc.py
dialog_api/crypto_pb2.py
dialog_api/crypto_pb2_grpc.py
dialog_api/definitions_pb2.py
dialog_api/definitions_pb2_grpc.py
dialog_api/device_info_pb2.py
dialog_api/device_info_pb2_grpc.py
dialog_api/error_details_pb2.py
dialog_api/error_details_pb2_grpc.py
dialog_api/event_bus_pb2.py
dialog_api/event_bus_pb2_grpc.py
dialog_api/events_pb2.py
dialog_api/events_pb2_grpc.py
dialog_api/gateway_service_pb2.py
dialog_api/gateway_service_pb2_grpc.py
dialog_api/groups_pb2.py
dialog_api/groups_pb2_grpc.py
dialog_api/integrations_pb2.py
dialog_api/integrations_pb2_grpc.py
dialog_api/media_and_files_pb2.py
dialog_api/media_and_files_pb2_grpc.py
dialog_api/messaging_pb2.py
dialog_api/messaging_pb2_grpc.py
dialog_api/miniappsregistry_pb2.py
dialog_api/miniappsregistry_pb2_grpc.py
dialog_api/miscellaneous_pb2.py
dialog_api/miscellaneous_pb2_grpc.py
dialog_api/obsolete_pb2.py
dialog_api/obsolete_pb2_grpc.py
dialog_api/peers_pb2.py
dialog_api/peers_pb2_grpc.py
dialog_api/permissions_pb2.py
dialog_api/permissions_pb2_grpc.py
dialog_api/presence_pb2.py
dialog_api/presence_pb2_grpc.py
dialog_api/privacy_pb2.py
dialog_api/privacy_pb2_grpc.py
dialog_api/profile_pb2.py
dialog_api/profile_pb2_grpc.py
dialog_api/push_content_pb2.py
dialog_api/push_content_pb2_grpc.py
dialog_api/push_pb2.py
dialog_api/push_pb2_grpc.py
dialog_api/raw_api_pb2.py
dialog_api/raw_api_pb2_grpc.py
dialog_api/reactions_pb2.py
dialog_api/reactions_pb2_grpc.py
dialog_api/registration_pb2.py
dialog_api/registration_pb2_grpc.py
dialog_api/search_pb2.py
dialog_api/search_pb2_grpc.py
dialog_api/sequence_and_updates_pb2.py
dialog_api/sequence_and_updates_pb2_grpc.py
dialog_api/spaces_pb2.py
dialog_api-1.901.0.dist-info/LICENSE
dialog_api-1.901.0.dist-info/METADATA
dialog_api-1.901.0.dist-info/WHEEL
dialog_api-1.901.0.dist-info/top_level.txt
dialog_api-1.901.0.dist-info/RECORD
