Metadata-Version: 2.1
Name: dialog-api
Version: 1.901.0
Summary: Dialog API for Python
Home-page: https://github.com/dialogs/api-schema
Author: Dialog LLC
Author-email: services@dlg.im
License: Apache License 2.0
Keywords: dialog messenger
Platform: UNKNOWN
Classifier: Programming Language :: Python :: 3
Classifier: License :: OSI Approved :: Apache Software License
Classifier: Operating System :: OS Independent
Requires-Python: >=3
License-File: LICENSE
